{
	"ABI version": 2,
	"header": ["pubkey", "time", "expire"],
	"functions": [
		{
			"name": "constructor",
			"inputs": [
			],
			"outputs": [
			]
		},
		{
			"name": "sendWithCommission",
			"inputs": [
				{"name":"dest","type":"address"},
				{"name":"amount","type":"uint128"}
			],
			"outputs": [
			]
		},
		{
			"name": "sendmoney",
			"inputs": [
				{"name":"dest","type":"address"},
				{"name":"amount","type":"uint128"}
			],
			"outputs": [
			]
		},
		{
			"name": "sendAndDelete",
			"inputs": [
				{"name":"dest","type":"address"},
				{"name":"amount","type":"uint128"}
			],
			"outputs": [
			]
		}
	],
	"data": [
	],
	"events": [
	]
}
